<xml>

<dir>
  <title>[B][COLOR yellowgreen]•[/COLOR][COLOR purple]•[/COLOR][COLORsnow] Movie Years[/COLOR][/B]</title>
  <link>https://raw.githubusercontent.com/Shark5588/wtf/master/movie-years.xml</link>
</dir>

<dir>
  <title>[B][COLOR yellowgreen]•[/COLOR][COLOR purple]•[/COLOR][COLORsnow] Movie Genres[/COLOR][/B]</title>
  <link>https://raw.githubusercontent.com/Shark5588/wtf/master/genre_movies.xml</link>
</dir>

<plugin>
  <title>[B][COLOR yellowgreen]•[/COLOR][COLOR purple]•[/COLOR][COLORsnow] Movies PlayList[/COLOR][/B]</title>
  <link>plugin://plugin.video.live.streamspro/?mode=1&url=https://raw.githubusercontent.com/Shark5588/wtf/master/WTFlist1.xml</link>
</plugin> 

<dir>
  <title>[B][COLOR yellowgreen]•[/COLOR][COLOR purple]•[/COLOR][COLORsnow] Boxsets[/COLOR][/B]</title>
  <link>https://bit.ly/2rBpHik</link>
</dir>
  
<dir>
  <title>[B][COLOR yellowgreen]•[/COLOR][COLOR purple]•[/COLOR][COLORlime] ([/COLOR][COLORred] TMDB [/COLOR][COLORlime])[/COLOR][COLORsnow] Popular Movies[/COLOR][/B]</title>
  <tmdb>movies/popular</tmdb>
</dir>

<dir>
  <title>[B][COLOR yellowgreen]•[/COLOR][COLOR purple]•[/COLOR][COLORlime] ([/COLOR][COLORred] TMDB [/COLOR][COLORlime])[/COLOR][COLORsnow] Now Playing Movies[/COLOR][/B]</title>
  <tmdb>movies/now_playing</tmdb>
</dir>

<dir>
  <title>[B][COLOR yellowgreen]•[/COLOR][COLOR purple]•[/COLOR][COLORlime] ([/COLOR][COLORred] TMDB [/COLOR][COLORlime])[/COLOR][COLORsnow] Top Rated Movies[/COLOR][/B]</title>
  <tmdb>movies/top_rated</tmdb>
</dir>

dir>
  <title>[B][COLOR yellowgreen]•[/COLOR][COLOR purple]•[/COLOR][COLORlime] ([/COLOR][COLORred] TMDB [/COLOR][COLORlime])[/COLOR][COLORsnow] Action Movies[/COLOR][/B]</title>
  <tmdb>genre/movies/28</tmdb>
</dir>

<dir>
  <title>[B][COLOR yellowgreen]•[/COLOR][COLOR purple]•[/COLOR][COLORlime] ([/COLOR][COLORred] IMDB [/COLOR][COLORlime])[/COLOR][COLORsnow] Trending Movies[/COLOR][/B]</title>
  <imdburl>movies/trending</imdburl>
</dir>

<dir>
  <title>[B][COLOR yellowgreen]•[/COLOR][COLOR purple]•[/COLOR][COLORlime] ([/COLOR][COLORred] TMDB [/COLOR][COLORlime])[/COLOR][COLORsnow] Star Wars Collection[/COLOR][/B]</title>
  <tmdb>collection/10</tmdb>
</dir>

<dir>
  <title>[B][COLOR yellowgreen]•[/COLOR][COLOR purple]•[/COLOR][COLORlime] ([/COLOR][COLORred] TMDB [/COLOR][COLORlime])[/COLOR][COLORlime] ([/COLOR][COLORred] Trakt [/COLOR][COLORlime])[/COLOR][COLORsnow] List[/COLOR][/B]</title>
  <link>https://raw.githubusercontent.com/Shark5588/wtf/master/lists.xml</link>
</dir>

<plugin>
  <name>[B][COLOR yellowgreen]•[/COLOR][COLOR purple]•[/COLOR][COLORlime] ([/COLOR][COLORred] TORRENTS [/COLOR][COLORlime])[/COLOR][COLORsnow] THE MAG[/COLOR][/B]</name>
  <link>plugin://plugin.video.sports55classic/?fanart=https%3a%2f%2fwww.studioef.cz%2fwp-content%2fuploads%2f2017%2f10%2fthe-mag.png&amp;mode=1&amp;name=%5bB%5d%5bCOLOR%20yellowgreen%5d%e2%80%a2%5b%2fCOLOR%5d%5bCOLOR%20purple%5d%e2%80%a2%5b%2fCOLOR%5d%5bCOLORsnow%5d%20THE%20MAG%5b%2fCOLOR%5d%5bCOLORpurple%5dExperience%20Max%20Quality%5b%2fCOLOR%5d%5b%2fB%5d&amp;url=https%3a%2f%2fpastebin.com%2fraw%2fXXCy2cGm&quot;,return</link>
  <fanart>https://www.studioef.cz/wp-content/uploads/2017/10/the-mag.png</fanart>
  <thumbnail>http://pluspng.com/img-png/mag-png-mag-png-550.png</thumbnail>
</plugin>

</xml>